tensortools/__init__.py
tensortools/_hals_update.cpython-36m-darwin.so
tensortools/diagnostics.py
tensortools/ensemble.py
tensortools/operations.py
tensortools/tensors.py
tensortools/utils.py
tensortools/visualization.py
tensortools/data/__init__.py
tensortools/data/random_tensor.py
tensortools/optimize/__init__.py
tensortools/optimize/cp_als.py
tensortools/optimize/ncp_bcd.py
tensortools/optimize/ncp_hals.py
tensortools/optimize/optim_utils.py
tensortools-0.3.dist-info/DESCRIPTION.rst
tensortools-0.3.dist-info/METADATA
tensortools-0.3.dist-info/RECORD
tensortools-0.3.dist-info/WHEEL
tensortools-0.3.dist-info/metadata.json
tensortools-0.3.dist-info/top_level.txt
