Metadata-Version: 2.0
Name: tensortools
Version: 0.3
Summary: Tools for Tensor Decomposition.
Home-page: https://github.com/ahwillia/tensortools
Author: Alex Williams and N. Benjamin Erichson
Author-email: alex.h.willia@gmail.com
License: MIT
Keywords: tensor decomposition,canonical decomposition,parallel factors
Platform: UNKNOWN
Classifier: Intended Audience :: Science/Research
Classifier: Topic :: Scientific/Engineering :: Mathematics
Classifier: License :: OSI Approved :: MIT License
Classifier: Programming Language :: Python :: 3.5
Classifier: Programming Language :: Python :: 3.6
Requires-Dist: cython
Requires-Dist: numpy
Requires-Dist: scipy
Requires-Dist: tqdm
Requires-Dist: munkres
